[
  {
    "name": "Réka",
    "age": 11,
    "spokenLanguages": ["hun", "eng"],
    "school": "BGE",
    "subject": {
      "serviceType": "DEMAND",
      "address": {
        "display": "Budapest, XVIII. kerület"
      }
    },
    "roomType": "SHARED",
    "moveIntoAt": "2020-01-19T12:14:42.275Z",
    "price": {
      "currency": "HUF",
      "min": 40000,
      "max": 60000,
      "billsIncluded": false
    }
  },
  {
    "name": "Elemér",
    "age": 22,
    "spokenLanguages": ["hun", "eng"],
    "school": "METU",
    "subject": {
      "serviceType": "OFFER",
      "address": {
        "display": "Budapest, XVIII. kerület"
      }
    },
    "roomType": "SHARED",
    "moveIntoAt": "2020-01-19T12:14:42.275Z",
    "price": {
      "currency": "HUF",
      "min": 40000,
      "max": 60000,
      "billsIncluded": false
    }
  },
  {
    "name": "Tóbiás",
    "age": 33,
    "spokenLanguages": ["hun", "eng"],
    "school": "NYE",
    "subject": {
      "serviceType": "DEMAND",
      "address": {
        "display": "Budapest, XVIII. kerület"
      }
    },
    "roomType": "PRIVATE",
    "moveIntoAt": "2020-01-19T12:14:42.275Z",
    "price": {
      "currency": "HUF",
      "min": 40000,
      "max": 60000,
      "billsIncluded": false
    }
  },
  {
    "name": "Milán",
    "age": 44,
    "spokenLanguages": ["hun", "eng"],
    "school": "SE",
    "subject": {
      "serviceType": "OFFER",
      "address": {
        "display": "Budapest, XVIII. kerület"
      }
    },
    "roomType": "SHARED",
    "moveIntoAt": "2020-01-19T12:14:42.275Z",
    "price": {
      "currency": "EUR",
      "min": 40000,
      "max": 60000,
      "billsIncluded": false
    }
  },
  {
    "name": "Imola",
    "age": 55,
    "spokenLanguages": ["hun", "eng"],
    "school": "BCE",
    "subject": {
      "serviceType": "DEMAND",
      "address": {
        "display": "Budapest, XVIII. kerület"
      }
    },
    "roomType": "SHARED",
    "moveIntoAt": "2020-01-19T12:14:42.275Z",
    "price": {
      "currency": "HUF",
      "min": 40000,
      "max": 60000,
      "billsIncluded": false
    }
  },
  {
    "name": "Gerda",
    "age": 66,
    "spokenLanguages": ["hun", "eng"],
    "school": "SSZHF",
    "subject": {
      "serviceType": "OFFER",
      "address": {
        "display": "Budapest, XVIII. kerület"
      }
    },
    "roomType": "PRIVATE",
    "moveIntoAt": "2020-01-19T12:14:42.275Z",
    "price": {
      "currency": "HUF",
      "min": 40000,
      "max": 60000,
      "billsIncluded": false
    }
  },
  {
    "name": "Zsuzsanna",
    "age": 77,
    "spokenLanguages": ["hun", "eng"],
    "school": "VHF",
    "subject": {
      "serviceType": "DEMAND",
      "address": {
        "display": "Budapest, XVIII. kerület"
      }
    },
    "roomType": "SHARED",
    "moveIntoAt": "2020-01-19T12:14:42.275Z",
    "price": {
      "currency": "HUF",
      "min": 40000,
      "max": 60000,
      "billsIncluded": false
    }
  },
  {
    "name": "Imre",
    "age": 88,
    "spokenLanguages": ["hun", "eng"],
    "school": "EJF",
    "subject": {
      "serviceType": "OFFER",
      "address": {
        "display": "Budapest, XVIII. kerület"
      }
    },
    "roomType": "SHARED",
    "moveIntoAt": "2020-01-19T12:14:42.275Z",
    "price": {
      "currency": "HUF",
      "min": 40000,
      "max": 60000,
      "billsIncluded": false
    }
  },
  {
    "name": "Ivett",
    "age": 99,
    "spokenLanguages": ["hun", "eng"],
    "school": "ELTE",
    "subject": {
      "serviceType": "DEMAND",
      "address": {
        "display": "Budapest, XVIII. kerület"
      }
    },
    "roomType": "PRIVATE",
    "moveIntoAt": "2020-01-19T12:14:42.275Z",
    "price": {
      "currency": "HUF",
      "min": 40000,
      "max": 60000,
      "billsIncluded": false
    }
  },
  {
    "name": "Anna",
    "age": 10,
    "spokenLanguages": ["hun", "eng"],
    "school": "BME",
    "subject": {
      "serviceType": "OFFER",
      "address": {
        "display": "Budapest, XVIII. kerület"
      }
    },
    "roomType": "SHARED",
    "moveIntoAt": "2020-01-19T12:14:42.275Z",
    "price": {
      "currency": "HUF",
      "min": 40000,
      "max": 60000,
      "billsIncluded": false
    }
  },
  {
    "name": "Bendegúz",
    "age": 20,
    "spokenLanguages": ["hun", "eng"],
    "school": "SZTE",
    "subject": {
      "serviceType": "DEMAND",
      "address": {
        "display": "Budapest, XVIII. kerület"
      }
    },
    "roomType": "SHARED",
    "moveIntoAt": "2020-01-19T12:14:42.275Z",
    "price": {
      "currency": "HUF",
      "min": 40000,
      "max": 60000,
      "billsIncluded": false
    }
  },
  {
    "name": "Rezeda",
    "age": 30,
    "spokenLanguages": ["hun", "eng"],
    "school": "SZIE",
    "subject": {
      "serviceType": "OFFER",
      "address": {
        "display": "Budapest, XVIII. kerület"
      }
    },
    "roomType": "PRIVATE",
    "moveIntoAt": "2020-01-19T12:14:42.275Z",
    "price": {
      "currency": "HUF",
      "min": 40000,
      "max": 60000,
      "billsIncluded": false
    }
  },
  {
    "name": "Petra",
    "age": 40,
    "spokenLanguages": ["hun", "eng"],
    "school": "KJE",
    "subject": {
      "serviceType": "DEMAND",
      "address": {
        "display": "Budapest, XVIII. kerület"
      }
    },
    "roomType": "SHARED",
    "moveIntoAt": "2020-01-19T12:14:42.275Z",
    "price": {
      "currency": "EUR",
      "min": 40000,
      "max": 60000,
      "billsIncluded": false
    }
  }
]
